quran/Errors.py
quran/MiddleWare.py
quran/Quran_api.py
quran/Sunnah_api.py
quran/__init__.py
quran/extractMethods.py
quran-1.0.0.dist-info/METADATA
quran-1.0.0.dist-info/WHEEL
quran-1.0.0.dist-info/top_level.txt
quran-1.0.0.dist-info/RECORD
