Metadata-Version: 2.1
Name: quran
Version: 1.0.0
Summary: A python wrapper quran.com api.
Home-page: https://github.com/dreygur/Quran.com/tree/master
Author: dreygur
Author-email: ryeasin03@gmail.com
License: MIT
Keywords: quran api
Platform: any
Classifier: Development Status :: 4 - Beta
Classifier: Intended Audience :: Developers
Classifier: License :: OSI Approved :: MIT License
Classifier: Topic :: Software Development :: Libraries :: Python Modules
Classifier: Programming Language :: Python :: 3.8
